{
  "pmid": "31112312",
  "title": "Invited Review: Pathology of pituitary neuroendocrine tumours: present status, modern diagnostic approach, controversies and future perspectives from a neuropathological and clinical standpoint.",
  "abstract": "Neuroendocrine tumours of the adenohypophysis have traditionally been designated as pituitary adenomas to underline their usually indolent growth and lack of metastatic potential. However, they may demonstrate a huge spectrum of growth patterns and endocrine disturbances, some of them significantly affecting health and quality of life. To predict tumour growth, risk of postoperative recurrence and response to medical therapy in patients with pituitary neuroendocrine tumours is challenging. A thorough histopathological and immunohistochemical diagnostic work-up is an obligatory part of a multidisciplinary effort to precisely define the tumour type and assess prognostic and predictive factors on an individual basis. In this review, we have summarized the current status in the pathology in pituitary neuroendocrine tumours based on the selection of references from the PubMed database. We have presented possible diagnostic approaches according to the current pituitary cell lineage-based classification. The importance of recognizing histological subtypes with potentially aggressive behaviour and identification of prognostic and predictive tissue biomarkers have been highlighted. Controversies related to particular subtypes of pituitary tumours and a still limited prognostic impact of the current classification indicate the need for further refinement. Multidisciplinary approach including clinical, pathological and molecular genetic characterization will be essential for improved personalized therapy and the search for novel therapeutic targets in patients with pituitary neuroendocrine tumours.",
  "journal": "Neuropathology and applied neurobiology",
  "year": "2021",
  "authors": [
    "Manojlovic-Gacic E",
    "Bollerslev J",
    "Casar-Borota O"
  ],
  "mesh_terms": [
    "Adenoma",
    "Humans",
    "Neuroendocrine Tumors",
    "Neuropathology",
    "Pituitary Neoplasms"
  ]
}