{
  "pmid": "32030200",
  "title": "Chinese Stroke Association guidelines for clinical management of cerebrovascular disorders: executive summary and 2019 update of clinical management of spontaneous subarachnoid haemorrhage.",
  "abstract": "AIM: Spontaneous subarachnoid haemorrhage (SAH) caused by ruptured cerebral aneurysm is a severe subtype of haemorrhagic stroke. Although the incidence of SAH is relatively low among all cerebrovascular diseases, the mortality is the highest. The critical management of SAH is challenging. We provide this evidence-based guideline to present current and comprehensive recommendations for the diagnosis and treatment of non-trauma SAH. METHODS: A formal literature search of MEDLINE (1 January 1990-30 June 2019) was performed. Data were synthesised with the use of evidence tables. Writing group members met by teleconference to discuss data-derived recommendations. The Chinese Stroke Association's levels of evidence grading algorithm was used to grade each recommendation. The guideline draft was reviewed by Chinese Stroke Association's Stroke Fellow Committees. It is intended that this guideline be fully updated every 3 years. RESULTS: Evidence-based guidelines are presented for the care of patients presenting with non-trauma SAH. The focus of the guideline was subdivided into transfer and systems of care, diagnosis flowchart, aetiology and differentiation, prevention of rebleeding, surgical and endovascular repair of ruptured aneurysms, management of vasospasm and delayed cerebral ischaemia, management of hydrocephalus, management of seizures and management of medical complications. CONCLUSIONS: The guideline offers a framework for SAH management. Early professional and aggressive care of SAH might help dramatically.",
  "journal": "Stroke and vascular neurology",
  "year": "2021",
  "authors": [
    "Dong Y",
    "Guo ZN",
    "Li Q",
    "Ni W",
    "Gu H",
    "Gu YX",
    "Dong Q"
  ],
  "mesh_terms": [
    "China",
    "Consensus",
    "Early Diagnosis",
    "Evidence-Based Medicine",
    "Humans",
    "Neurology",
    "Risk Factors",
    "Severity of Illness Index",
    "Subarachnoid Hemorrhage",
    "Time Factors",
    "Time-to-Treatment",
    "Treatment Outcome"
  ]
}