{
  "pmid": "32889955",
  "title": "Telemedicine in Behavioral Neurology-Neuropsychiatry: Opportunities and Challenges Catalyzed by COVID-19.",
  "abstract": "Coronavirus 2019 (COVID-19) has profoundly impacted the well-being of society and the practice of medicine across health care systems worldwide. As with many other subspecialties, the clinical paradigm in behavioral neurology and neuropsychiatry (BN-NP) was transformed abruptly, transitioning to real-time telemedicine for the assessment and management of the vast majorities of patient populations served by our subspecialty. In this commentary, we outline themes from the BN-NP perspective that reflect the emerging lessons we learned using telemedicine during the COVID-19 pandemic. Positive developments include the ability to extend consultations and management to patients in our high-demand field, maintenance of continuity of care, enhanced ecological validity, greater access to a variety of well-reimbursed telemedicine options (telephone and video) that help bridge the digital divide, and educational and research opportunities. Challenges include the need to adapt the mental state examination to the telemedicine environment, the ability to perform detailed motor neurologic examinations in patients where motor features are important diagnostic considerations, appreciating nonverbal cues, managing acute safety and behavioral concerns in less controlled environments, and navigating intervention-based (neuromodulation) clinics requiring in-person contact. We hope that our reflections help to catalyze discussions that should take place within the Society for Behavioral and Cognitive Neurology, the American Neuropsychiatric Association, and allied organizations regarding how to optimize real-time telemedicine practices for our subspecialty now and into the future.",
  "journal": "Cognitive and behavioral neurology : official journal of the Society for Behavioral and Cognitive Neurology",
  "year": "2020",
  "authors": [
    "Perez DL",
    "Biffi A",
    "Camprodon JA",
    "Caplan DN",
    "Chemali Z",
    "Kritzer MD",
    "Moo LR",
    "Newhouse AL",
    "Ramirez-Gomez L",
    "Razafsha M",
    "Tanev KS",
    "Schmahmann JD"
  ],
  "mesh_terms": [
    "Betacoronavirus",
    "COVID-19",
    "Coronavirus Infections",
    "Humans",
    "Massachusetts",
    "Nervous System Diseases",
    "Neurologic Examination",
    "Neurology",
    "Neuropsychiatry",
    "Pandemics",
    "Pneumonia, Viral",
    "SARS-CoV-2",
    "Telemedicine"
  ]
}