{
  "pmid": "34215383",
  "title": "Novel Treatments and Clinical Research in Child Neurology.",
  "abstract": "The molecular understanding of the pathogenic mechanisms responsible for neurologic diseases of children has led to a remarkable period of research that addresses the root causes of diseases. The promise of this research has been realized with cures and treatments that correct underlying deficiencies. The breakneck rate at which new research is being proposed promises to usher in a transformation of child neurology from a diagnostic and supportive field into an interventional one. Training child neurology residents in clinical research and therapeutic intervention is increasingly important to assure the ongoing ability to support research discoveries and treatment.",
  "journal": "Neurologic clinics",
  "year": "2021",
  "authors": [
    "Clark GD",
    "Lotze TE"
  ],
  "mesh_terms": [
    "Child",
    "Humans",
    "Internship and Residency",
    "Nervous System Diseases",
    "Neurology"
  ]
}