{
  "pmid": "34872316",
  "title": "Is there a need for advance care planning in China?-an interview survey of healthcare professionals in the neurology department.",
  "abstract": "BACKGROUND: Family-oriented medical decision-making in China is founded on Confucian family-determination. The value and necessity of individual autonomy are marginalized in theory and practice. However, the dilemma in end-of-life (EOL) decision-making caused by the lack of advance care planning (ACP) has been increasingly concerned by the public. This study explores the value and necessity of ACP practice in China from the perspective of healthcare professionals (HCPs). METHODS: We conducted semi-structured interviews with five neurological physicians and five neurological nurses from a Grade 3 Class A hospital in Beijing. RESULTS: The results showed that in situations with a poor prognosis, respondents tended to believe that as part of ACP regarding, a patient's right to refuse invasive treatments should be followed, although all ten interviewees agreed that nasogastric feeding tubes (NGTs) should be maintained. Factors influencing a families' considerations in EOL decision making included prognosis and age, prior similar experiences, others' moral judgement, and the advice of HCPs. Four respondents had experienced patients expressing their wishes for EOL treatments and reported some obstacles in considering these wishes. Seven respondents considered creating an ACP themselves, two respondents doubted it would work in practice, and one respondent thought it was unnecessary. CONCLUSIONS: The differences in the concept and practice of palliative care may be significantly related to the differences in the idea of ACP between Chinese and Western. The family-oriented decision-making model under Confucian culture cannot replace the ACP practice. Clinical situations and therapeutic measures that reveal the necessity and value of ACP should be the priority exploration to advance ACP practice. The practice of ACP and palliative care should be promoted simultaneously at the national level, and legislation for advance directives (ADs) is necessary for mainland China.",
  "journal": "Annals of palliative medicine",
  "year": "2021",
  "authors": [
    "Huang Y",
    "Liu H"
  ],
  "mesh_terms": [
    "Advance Care Planning",
    "China",
    "Delivery of Health Care",
    "Humans",
    "Neurology",
    "Surveys and Questionnaires"
  ]
}